natural2lean/__init__.py
natural2lean/translator.py
natural2lean/algebra/__init__.py
natural2lean/algebra/algebra.py
natural2lean/algebra/equation.py
natural2lean/algebra/expression.py
natural2lean/algebra/expression_possibilities.py
natural2lean/algebra/identifiers.py
natural2lean/algebra/translate_math.py
natural2lean/algebra/translation_constants.py
natural2lean/lean_interaction/__init__.py
natural2lean/lean_interaction/conclude_proof.py
natural2lean/lean_interaction/lean_feedback.py
natural2lean/proof_elements/__init__.py
natural2lean/proof_elements/statement/__init__.py
natural2lean/proof_elements/statement/have.py
natural2lean/proof_elements/statement/induction.py
natural2lean/proof_elements/statement/induction_case.py
natural2lean/proof_elements/statement/proof_structure.py
natural2lean/proof_elements/statement/simple_statements.py
natural2lean/proof_elements/statement/statement.py
natural2lean/proof_elements/theorem/__init__.py
natural2lean/proof_elements/theorem/example.py
natural2lean/proof_elements/theorem/named_theorem.py
natural2lean/proof_elements/theorem/theorem.py
natural2lean/propositions/__init__.py
natural2lean/propositions/function.py
natural2lean/propositions/implication.py
natural2lean/propositions/multiple_propositions.py
natural2lean/propositions/proposition.py
natural2lean/propositions/proposition_constants.py
natural2lean/propositions/separate_propositions.py
natural2lean/propositions/such_that.py
natural2lean/utils/__init__.py
natural2lean/utils/exceptions.py
natural2lean/utils/git_management.py
natural2lean/utils/text.py
natural2lean/utils/translatable.py
natural2lean/utils/unfolding.py
natural2lean-0.0.6.dist-info/LICENSE
natural2lean-0.0.6.dist-info/METADATA
natural2lean-0.0.6.dist-info/WHEEL
natural2lean-0.0.6.dist-info/top_level.txt
natural2lean-0.0.6.dist-info/RECORD
