Metadata-Version: 2.1
Name: natural2lean
Version: 0.0.6
Summary: Translation of proofs from Natural Language to Lean
Home-page: https://github.com/Augustindou/natural2lean
Author: Augustin d'Oultremont
Author-email: Augustin d'Oultremont <augustin.doultremont@outlook.com>
License: MIT License        
Project-URL: Homepage, https://github.com/Augustindou/natural2lean
Keywords: auto-formalization,parser
Classifier: License :: OSI Approved :: MIT License
Classifier: Programming Language :: Python
Classifier: Programming Language :: Python :: 3
Requires-Python: >=3.9
License-File: LICENSE
Provides-Extra: dev
Requires-Dist: pytest (>=3.6) ; extra == 'dev'
Requires-Dist: black ; extra == 'dev'
